pyxel_lander/__init__.py
pyxel_lander/__main__.py
pyxel_lander/assets/assets.pyxres
pyxel_lander/constants.py
pyxel_lander/game.py
pyxel_lander/lunar_module.py
pyxel_lander/moon.py
pyxel_lander/utils.py
pyxel_lander-1.4.0.dist-info/entry_points.txt
pyxel_lander-1.4.0.dist-info/LICENSE
pyxel_lander-1.4.0.dist-info/WHEEL
pyxel_lander-1.4.0.dist-info/METADATA
pyxel_lander-1.4.0.dist-info/RECORD
