Metadata-Version: 2.1
Name: pyxel-lander
Version: 1.4.0
Summary: Lunar Lander game tribute written in Python with Pyxel retro game engine
Home-page: https://github.com/humrochagf/pyxel-lander
License: MIT
Author: Humberto Rocha
Author-email: humrochagf@gmail.com
Requires-Python: >=3.7,<4.0
Classifier: Environment :: X11 Applications
Classifier: License :: OSI Approved :: MIT License
Classifier: Natural Language :: English
Classifier: Operating System :: OS Independent
Classifier: Programming Language :: Python :: 3
Classifier: Programming Language :: Python :: 3.10
Classifier: Programming Language :: Python :: 3.7
Classifier: Programming Language :: Python :: 3.8
Classifier: Programming Language :: Python :: 3.9
Classifier: Topic :: Desktop Environment
Classifier: Topic :: Games/Entertainment :: Arcade
Classifier: Topic :: Games/Entertainment :: Simulation
Requires-Dist: pyxel (>=1.5.5,<2.0.0)
Project-URL: Repository, https://github.com/humrochagf/pyxel-lander
